<compatibility-matrix version="2.0" type="framework">
    <hal format="hidl" optional="true">
        <name>vendor.egistec.hardware.fingerprint</name>
        <transport>hwbinder</transport>
        <version>4.0</version>
        <interface>
            <name>IBiometricsFingerprintRbs</name>
            <instance>default</instance>
        </interface>
    </hal>
    <hal format="hidl" optional="true">
        <name>vendor.qti.hardware.servicetracker</name>
        <transport>hwbinder</transport>
        <version>1.2</version>
        <interface>
            <name>IServicetracker</name>
        </interface>
    </hal>
    <hal format="hidl" optional="true">
        <name>vendor.qti.hardware.qccsyshal</name>
        <version>1.0-2</version>
        <interface>
            <name>IQccsyshal</name>
            <instance>qccsyshal</instance>
        </interface>
    </hal>
</compatibility-matrix>
